aresTools/featurizer.py
aresTools-0.0.1.dist-info/METADATA
aresTools-0.0.1.dist-info/WHEEL
aresTools-0.0.1.dist-info/top_level.txt
aresTools-0.0.1.dist-info/RECORD
