Metadata-Version: 2.1
Name: aresTools
Version: 0.0.1
Summary: A Python package that transforms a pandas DataFrame based on mathematical operations described on JSON
Home-page: https://github.com/aresmaterials/arestools
Author: Erik Gutierrez-Valladares
Author-email: erik@aresmaterials.com
License: Apache License 2.0
Platform: UNKNOWN
Requires-Dist: pandas
